dtnsim/__init__.py
dtnsim/scheduler.py
dtnsim/vector.py
dtnsim/agent/__init__.py
dtnsim/agent/carryonly.py
dtnsim/agent/epidemic.py
dtnsim/agent/hp_bcast.py
dtnsim/agent/p_bcast.py
dtnsim/agent/prophet.py
dtnsim/agent/random.py
dtnsim/agent/sa_bcast.py
dtnsim/mobility/__init__.py
dtnsim/mobility/fixed.py
dtnsim/mobility/fullmixed.py
dtnsim/mobility/levywalk.py
dtnsim/mobility/limited_rwp.py
dtnsim/mobility/limited_rwp_flylint.py
dtnsim/mobility/randomwalk.py
dtnsim/mobility/rwp.py
dtnsim/mobility/graph/__init__.py
dtnsim/mobility/graph/crwp.py
dtnsim/mobility/graph/crwp_flylint.py
dtnsim/mobility/graph/fixed.py
dtnsim/mobility/graph/fixed_flylint.py
dtnsim/mobility/graph/randomwalk.py
dtnsim/mobility/graph/sequential.py
dtnsim/mobility/graph/sequential_flylint.py
dtnsim/monitor/__init__.py
dtnsim/monitor/cell.py
dtnsim/monitor/log.py
dtnsim/monitor/null.py
dtnsim/path/__init__.py
dtnsim/path/grid.py
dtnsim/path/line.py
dtnsim/path/none.py
dtnsim/path/voronoi.py
dtnsim-1.7.data/scripts/dtnsim
dtnsim-1.7.dist-info/LICENSE
dtnsim-1.7.dist-info/METADATA
dtnsim-1.7.dist-info/WHEEL
dtnsim-1.7.dist-info/top_level.txt
dtnsim-1.7.dist-info/RECORD
