Metadata-Version: 2.1
Name: dtnsim
Version: 1.7
Summary: DTN (Delay/Disruption Tolerant Networking) simulator with several agent/mobility models
Home-page: https://github.com/h-ohsaki/dtnsim
Author: Hiroyuki Ohsaki
Author-email: ohsaki@lsnl.jp
Classifier: Programming Language :: Python :: 3
Classifier: License :: OSI Approved :: GNU General Public License v3 (GPLv3)
Classifier: Operating System :: OS Independent
License-File: LICENSE
Requires-Dist: Pytess
Requires-Dist: cellx
Requires-Dist: graph-tools
Requires-Dist: perlcompat
